domotica_fhz/__init__.py
domotica_fhz/fhz.py
domotica_fhz/domotica_fhz_tests/__init__.py
domotica_fhz/domotica_fhz_tests/test_fhz.py
domotica_fhz-0.0.1.dist-info/LICENSE
domotica_fhz-0.0.1.dist-info/METADATA
domotica_fhz-0.0.1.dist-info/WHEEL
domotica_fhz-0.0.1.dist-info/top_level.txt
domotica_fhz-0.0.1.dist-info/RECORD
