Metadata-Version: 2.1
Name: domotica-fhz
Version: 0.0.1
Summary: Package for using the FHZ 1000/FHZ 1300/FS20
Home-page: https://gitlab.com/JohanKunnen/domotica_fhz
Author: Johan Kunnen
Author-email: domotica@kunnen.frl
License: UNKNOWN
Platform: UNKNOWN
Classifier: Programming Language :: Python :: 3
Classifier: License :: OSI Approved :: MIT License
Classifier: Operating System :: OS Independent
